[
  {
    "id": 1,
    "username": "testuser",
    "email": "test@example.com",
    "password": "password123",
    "createdAt": "2025-08-11T17:59:51.081Z",
    "lastLogin": "2025-08-13T08:26:55.866Z"
  },
  {
    "id": 2,
    "username": "test",
    "email": "test@test.com",
    "password": "Hbd@681727",
    "createdAt": "2025-08-11T18:12:35.358Z",
    "lastLogin": "2025-08-12T10:58:29.343Z"
  },
  {
    "id": 3,
    "username": "hmm",
    "email": "hmm@hmm.com",
    "password": "Hbd@681727",
    "createdAt": "2025-08-12T20:10:41.824Z",
    "lastLogin": "2025-08-12T20:18:07.015Z"
  },
  {
    "id": 4,
    "username": "testuser_1755073615872",
    "email": "test_1755073615872@example.com",
    "password": "testpassword123",
    "createdAt": "2025-08-13T08:26:55.874Z",
    "lastLogin": null
  }
]